halludetector/__init__.py
halludetector/config.py
halludetector/scorer.py
halludetector/checker/__init__.py
halludetector/checker/checker.py
halludetector/checker/checker_base.py
halludetector/checker/gpt4_checker.py
halludetector/datasets/__init__.py
halludetector/datasets/covid_qa.py
halludetector/datasets/databricks_dolly.py
halludetector/datasets/drop.py
halludetector/datasets/parser.py
halludetector/detectors/__init__.py
halludetector/detectors/base.py
halludetector/detectors/chainpoll.py
halludetector/detectors/custom.py
halludetector/detectors/geval.py
halludetector/detectors/refchecker.py
halludetector/detectors/selfcheckgpt.py
halludetector/extractor/__init__.py
halludetector/extractor/claude2_extractor.py
halludetector/extractor/extractor.py
halludetector/extractor/extractor_base.py
halludetector/extractor/gpt4_extractor.py
halludetector/extractor/mistral_extractor.py
halludetector/extractor/mixtral_extractor.py
halludetector/generators/__init__.py
halludetector/generators/question.py
halludetector/llm/__init__.py
halludetector/llm/mistral.py
halludetector/llm/openai.py
halludetector/prompts/__init__.py
halludetector/prompts/default.py
halludetector/retrievers/__init__.py
halludetector/retrievers/google_retriever.py
halludetector/retrievers/retriever.py
halludetector-0.0.8.dist-info/METADATA
halludetector-0.0.8.dist-info/WHEEL
halludetector-0.0.8.dist-info/top_level.txt
halludetector-0.0.8.dist-info/RECORD
